streamlit_copy_to_clipboard_button/__init__.py
streamlit_copy_to_clipboard_button/example.py
streamlit_copy_to_clipboard_button/py.typed
streamlit_copy_to_clipboard_button/frontend/build/asset-manifest.json
streamlit_copy_to_clipboard_button/frontend/build/bootstrap.min.css
streamlit_copy_to_clipboard_button/frontend/build/index.html
streamlit_copy_to_clipboard_button/frontend/build/static/js/main.ff027263.js
streamlit_copy_to_clipboard_button/frontend/build/static/js/main.ff027263.js.LICENSE.txt
streamlit_copy_to_clipboard_button/frontend/build/static/js/main.ff027263.js.map
streamlit_copy_to_clipboard_button-1.0.7.dist-info/METADATA
streamlit_copy_to_clipboard_button-1.0.7.dist-info/WHEEL
streamlit_copy_to_clipboard_button-1.0.7.dist-info/top_level.txt
streamlit_copy_to_clipboard_button-1.0.7.dist-info/RECORD
