Metadata-Version: 2.4
Name: streamlit-copy-to-clipboard-button
Version: 1.0.7
Summary: A Streamlit copy-to-clipboard button component that respects the streamlit page styles.
Author-email: Sam Sze <mingsum.sam@gmail.com>
License-Expression: MIT
Project-URL: Homepage, https://github.com/samsze0/streamlit-copy-to-clipboard-button
Project-URL: Repository, https://github.com/samsze0/streamlit-copy-to-clipboard-button
Keywords: streamlit,copy,clipboard,button,component
Requires-Python: >=3.13
Requires-Dist: streamlit>=1.45.1
